radio_curses/__init__.py
radio_curses/__main__.py
radio_curses/db.py
radio_curses/utils.py
radio_curses/curses_utils/__init__.py
radio_curses/curses_utils/list1.py
radio_curses/curses_utils/list1m.py
radio_curses-0.13.1.dist-info/METADATA
radio_curses-0.13.1.dist-info/WHEEL
radio_curses-0.13.1.dist-info/entry_points.txt
radio_curses-0.13.1.dist-info/licenses/LICENSE
radio_curses-0.13.1.dist-info/RECORD
