Metadata-Version: 2.4
Name: radio-curses
Version: 0.13.1
Summary: A OPML radio player
Project-URL: homepage, https://github.com/shamilbi/radio-curses
Author-email: Shamil Bikineyev <shamilbi@gmail.com>
License-Expression: MIT
License-File: LICENSE
Keywords: internet,radio
Classifier: Development Status :: 4 - Beta
Classifier: Environment :: Console
Classifier: Natural Language :: English
Classifier: Operating System :: POSIX :: Linux
Classifier: Programming Language :: Python
Classifier: Programming Language :: Python :: 3
Classifier: Programming Language :: Python :: 3 :: Only
Classifier: Programming Language :: Python :: 3.9
Classifier: Programming Language :: Python :: 3.10
Classifier: Programming Language :: Python :: 3.11
Classifier: Programming Language :: Python :: 3.12
Classifier: Programming Language :: Python :: 3.13
Classifier: Programming Language :: Python :: Implementation :: CPython
Requires-Python: >=3.9
Requires-Dist: lxml
Requires-Dist: requests
Requires-Dist: xdg-base-dirs
